embeddr_core/py.typed
embeddr_core/models/__init__.py
embeddr_core/models/collection.py
embeddr_core/models/library.py
embeddr_core/models/lineage.py
embeddr_core/services/embedding.py
embeddr_core/services/embedding_manager.py
embeddr_core/services/job_manager.py
embeddr_core/services/scanner.py
embeddr_core/services/thumbnails.py
embeddr_core/services/vector_store.py
embeddr_core-0.1.5.dist-info/licenses/LICENSE.md
embeddr_core-0.1.5.dist-info/METADATA
embeddr_core-0.1.5.dist-info/WHEEL
embeddr_core-0.1.5.dist-info/top_level.txt
embeddr_core-0.1.5.dist-info/RECORD
