Metadata-Version: 2.4
Name: embeddr-core
Version: 0.1.5
Summary: Embeddr Core Library
Author-email: Nynxz <contact@nynxz.com>
Project-URL: Homepage, https://github.com/embeddr-net/embeddr-core
Project-URL: Repository, https://github.com/embeddr-net/embeddr-core
Project-URL: Issues, https://github.com/embeddr-net/embeddr-core/issues
Requires-Python: >=3.12
License-File: LICENSE.md
Requires-Dist: ruff>=0.14.10
Requires-Dist: sqlmodel>=0.0.29
Requires-Dist: pillow>=12.0.0
Requires-Dist: numpy>=2.4.0
Requires-Dist: transformers>=4.57.3
Requires-Dist: tqdm>=4.66.0
Provides-Extra: torch
Requires-Dist: torch>=2.9; extra == "torch"
Provides-Extra: dev
Requires-Dist: pytest; extra == "dev"
Requires-Dist: ruff; extra == "dev"
Dynamic: license-file
